sudhanshu090911/__init__.py
sudhanshu090911-0.1.0.dist-info/METADATA
sudhanshu090911-0.1.0.dist-info/WHEEL
sudhanshu090911-0.1.0.dist-info/top_level.txt
sudhanshu090911-0.1.0.dist-info/RECORD
